pyidp3/__init__.py
pyidp3/communicator.py
pyidp3/idp_parse_out.py
pyidp3/idp_py_syntax.py
pyidp3/idpobjects.py
pyidp3/typedIDP.py
pyidp3-0.0.9.dist-info/LICENSE
pyidp3-0.0.9.dist-info/METADATA
pyidp3-0.0.9.dist-info/WHEEL
pyidp3-0.0.9.dist-info/top_level.txt
pyidp3-0.0.9.dist-info/RECORD
