Metadata-Version: 2.1
Name: pyidp3
Version: 0.0.9
Summary: A Python3 to IDP API
Home-page: https://gitlab.com/Salt_Factory/pyidp3
Author: Simon Vandevelde
Author-email: s.vandevelde@kuleuven.be
License: UNKNOWN
Platform: UNKNOWN
License-File: LICENSE
